ecommerce_mcp/__init__.py
ecommerce_mcp/main.py
ecommerce_mcp/models.py
ecommerce_mcp/server.py
ecommerce_mcp/sites/__init__.py
ecommerce_mcp/sites/base.py
ecommerce_mcp/sites/jingdong.py
ecommerce_mcp/sites/taobao.py
ecommerce_mcp-0.1.0.dist-info/METADATA
ecommerce_mcp-0.1.0.dist-info/WHEEL
ecommerce_mcp-0.1.0.dist-info/entry_points.txt
ecommerce_mcp-0.1.0.dist-info/RECORD
