Metadata-Version: 2.4
Name: ecommerce_mcp
Version: 0.1.0
Summary: MCP server for searching products on Chinese e-commerce sites (Taobao, Jingdong)
Requires-Python: >=3.11
Requires-Dist: debugpy>=1.8.20
Requires-Dist: httpx>=0.28.1
Requires-Dist: mcp[cli]>=1.25.0
Requires-Dist: playwright>=1.40.0
Requires-Dist: pydantic>=2.5.0
Provides-Extra: dev
Requires-Dist: debugpy>=1.8.0; extra == 'dev'
Requires-Dist: pytest-asyncio>=0.23.0; extra == 'dev'
Requires-Dist: pytest>=8.0.0; extra == 'dev'
